{
  "battle-through-the-heaven-5": [
    {
      "id": "5",
      "image": "https://i.pinimg.com/736x/05/ee/5b/05ee5bcf5e365eb7544dac717ca3b745.jpg",
      "title": "Battle Through the Heaven - Xiao Yan",
      "season": "05",
      "episode": "110",
      "lastUpdated": "2024-08-27T15:30:00Z",
      "type": "Donghua",
      "video": [
        {
          "videoId": "110",
          "src": "https://geo.dailymotion.com/player.html?video=x94wppq",
          "episode": "110",
          "postingVideoDate": "2024-08-29T18:00:00Z"
        },
        {
          "videoId": "109",
          "src": "https://geo.dailymotion.com/player.html?video=x94w6k8",
          "episode": "109",
          "postingVideoDate": "2024-08-29T18:00:00Z"
        },
        {
          "videoId": "108",
          "src": "https://geo.dailymotion.com/player.html?video=x958n0q",
          "episode": "108",
          "postingVideoDate": "2024-08-29T18:00:00Z"
        },
        {
          "videoId": "107",
          "src": "https://geo.dailymotion.com/player.html?video=x958n66",
          "episode": "107",
          "postingVideoDate": "2024-08-29T18:00:00Z"
        },
        {
          "videoId": "106",
          "src": "https://geo.dailymotion.com/player.html?video=x958n9c",
          "episode": "106",
          "postingVideoDate": "2024-08-29T18:00:00Z"
        }
      ]
    }
  ]
}
